resumelyzer/__init__.py
resumelyzer/analyzer.py
resumelyzer/async_processor.py
resumelyzer/cache.py
resumelyzer/job_fit.py
resumelyzer/parser.py
resumelyzer/rate_limiter.py
resumelyzer/referral.py
resumelyzer/report_generator.py
resumelyzer-0.1.1.dist-info/entry_points.txt
resumelyzer-0.1.1.dist-info/METADATA
resumelyzer-0.1.1.dist-info/WHEEL
resumelyzer-0.1.1.dist-info/RECORD
