Metadata-Version: 2.3
Name: resumelyzer
Version: 0.1.1
Summary: AI-powered PDF resume parser with skill and personality profiling.
License: MIT
Author: Your Name
Author-email: laafiasarl@gmail.com
Requires-Python: >=3.9,<4.0
Classifier: License :: OSI Approved :: MIT License
Classifier: Programming Language :: Python :: 3
Classifier: Programming Language :: Python :: 3.9
Classifier: Programming Language :: Python :: 3.10
Classifier: Programming Language :: Python :: 3.11
Classifier: Programming Language :: Python :: 3.12
Classifier: Programming Language :: Python :: 3.13
Requires-Dist: fpdf2 (>=2.7.4,<3.0.0)
Requires-Dist: matplotlib (>=3.7.0,<4.0.0)
Requires-Dist: openai (>=1.14.1,<2.0.0)
Requires-Dist: pdfplumber (>=0.10.2,<0.11.0)
Requires-Dist: python-dotenv (>=1.0.0,<2.0.0)
